setup.cfg
setup.py
cabot_alert_pushover/__init__.py
cabot_alert_pushover/models.py
cabot_alert_pushover.egg-info/PKG-INFO
cabot_alert_pushover.egg-info/SOURCES.txt
cabot_alert_pushover.egg-info/dependency_links.txt
cabot_alert_pushover.egg-info/top_level.txt