Metadata-Version: 1.1
Name: cabot-alert-pushover
Version: 0.1
Summary: A Cabot plugin for sending alerts with Pushover
Home-page: https://github.com/packetcollision/cabot-alert-pushover/
Author: Daniel Nelson
Author-email: daniel@dcn.io
License: MIT
Download-URL: https://github.com/packetcollision/cabot-alert-pushover/tarball/0.1
Keywords: cabot alert
Platform: UNKNOWN
